api/__init__.py
api/convert.py
api/convert_using_openpyxl.py
excel2json/__init__.py
excel2json_3-0.1.6.dist-info/METADATA
excel2json_3-0.1.6.dist-info/RECORD
excel2json_3-0.1.6.dist-info/WHEEL
excel2json_3-0.1.6.dist-info/entry_points.txt
excel2json_3-0.1.6.dist-info/top_level.txt
