Metadata-Version: 2.1
Name: excel2json-3
Version: 0.1.6
Summary: Convert Excel Sheet into JSON file.
Home-page: https://github.com/toransahu/excel2json-3
Author: Toran Sahu
Author-email: toran.sahu@yahoo.com
License: Distributed under terms of the AGPL license.
Keywords: excel to json,xlsx to json,xls to json,xlsx,xls,json
Platform: UNKNOWN
Classifier: Programming Language :: Python :: 3
Classifier: Programming Language :: Python :: 3.6
Classifier: License :: OSI Approved :: GNU Affero General Public License v3 or later (AGPLv3+)
Classifier: Operating System :: OS Independent
Classifier: Topic :: Internet :: WWW/HTTP :: Indexing/Search
Classifier: Topic :: Software Development :: Libraries :: Python Modules
Classifier: Topic :: System :: Archiving :: Packaging
Classifier: Topic :: Text Processing
Classifier: Development Status :: 2 - Pre-Alpha
Classifier: Intended Audience :: Developers
Classifier: Intended Audience :: System Administrators
Classifier: Intended Audience :: End Users/Desktop
Classifier: Intended Audience :: Information Technology
Classifier: Natural Language :: English
